idissend/__init__.py
idissend/admin.py
idissend/cli.py
idissend/core.py
idissend/exceptions.py
idissend/orm.py
idissend/persistence.py
idissend/pipeline.py
idissend/stages.py
idissend-2.2.2.dist-info/AUTHORS.rst
idissend-2.2.2.dist-info/LICENSE
idissend-2.2.2.dist-info/METADATA
idissend-2.2.2.dist-info/WHEEL
idissend-2.2.2.dist-info/entry_points.txt
idissend-2.2.2.dist-info/top_level.txt
idissend-2.2.2.dist-info/RECORD
