Metadata-Version: 2.1
Name: idissend
Version: 2.2.2
Summary: Automate sending incoming files to IDIS anonymization server
Home-page: https://github.com/sjoerdk/idissend
Author: Sjoerd Kerkstra
Author-email: w.s.kerkstra@gmail.com
License: GNU General Public License v3
Keywords: idissend
Platform: UNKNOWN
Classifier: Development Status :: 2 - Pre-Alpha
Classifier: Intended Audience :: Developers
Classifier: License :: OSI Approved :: GNU General Public License v3 (GPLv3)
Classifier: Natural Language :: English
Classifier: Programming Language :: Python :: 3.6
Classifier: Programming Language :: Python :: 3.7
Classifier: Programming Language :: Python :: 3.8
Requires-Python: ~=3.6
Requires-Dist: Click (>=7.0)
Requires-Dist: sqlalchemy
Requires-Dist: anonapi
